pyemtmad/__init__.py
pyemtmad/types.py
pyemtmad/util.py
pyemtmad/wrapper.py
pyemtmad/api/__init__.py
pyemtmad/api/bus.py
pyemtmad/api/geo.py
pyemtmad/api/parking.py
pyemtmad-0.1.0.dist-info/DESCRIPTION.rst
pyemtmad-0.1.0.dist-info/METADATA
pyemtmad-0.1.0.dist-info/RECORD
pyemtmad-0.1.0.dist-info/WHEEL
pyemtmad-0.1.0.dist-info/metadata.json
pyemtmad-0.1.0.dist-info/top_level.txt
