Metadata-Version: 2.0
Name: pyemtmad
Version: 0.1.0
Summary: (Kind of) sane wrapper for the EMT API
Home-page: https://github.com/rmed/pyemtmad
Author: Rafael Medina García
Author-email: rafamedgar@gmail.com
License: GPLv2+
Keywords: madrid transport travel bus geo open data api
Platform: UNKNOWN
Requires-Dist: requests (>=2.9.1)
Requires-Dist: six (>=1.10.0)
